LICENSE.txt
MANIFEST.in
README.rst
setup.cfg
setup.py
common/__init__.py
common/admin.py
common/apps.py
common/forms.py
common/managers.py
common/authentication/__init__.py
common/authentication/custom_user_authentication.py
common/enums/__init__.py
common/enums/order_status.py
common/exceptions/__init__.py
common/exceptions/api_exceptions.py
common/imports/__init__.py
common/imports/django_imports.py
common/imports/interapp_imports.py
common/imports/logger_imports.py
common/imports/third_party_import.py
common/imports/utils_imports.py
common/migrations/0001_initial.py
common/migrations/0020_auto_20220622_1721.py
common/migrations/0021_auto_20220622_1741.py
common/migrations/0022_auto_20220626_1520.py
common/migrations/0023_alter_order_id.py
common/migrations/0024_brand_image.py
common/migrations/__init__.py
common/models/__init__.py
common/models/address.py
common/models/config.py
common/models/otp.py
common/models/token_blacklist.py
common/models/user.py
common/models/cart/__init__.py
common/models/cart/cart.py
common/models/order_management/__init__.py
common/models/order_management/order.py
common/models/order_management/order_address.py
common/models/order_management/order_items.py
common/models/product_management/__init__.py
common/models/product_management/attribute.py
common/models/product_management/attribute_value.py
common/models/product_management/attribute_value_mapping.py
common/models/product_management/brand.py
common/models/product_management/category.py
common/models/product_management/product.py
common/models/product_management/variant.py
common/models/product_management/variant_attribute_mapping.py
common/models/shop_management/__init__.py
common/models/shop_management/plan.py
common/models/shop_management/shop.py
common/models/shop_management/template.py
common/response/__init__.py
common/response/api_response.py
common/utils/__init__.py
common/utils/create_seed_data.py
common/utils/custom_pagination.py
common/utils/dict_2_obj.py
stb_core.egg-info/PKG-INFO
stb_core.egg-info/SOURCES.txt
stb_core.egg-info/dependency_links.txt
stb_core.egg-info/top_level.txt